LICENSE.md
README.md
setup.py
DataDoctor.egg-info/PKG-INFO
DataDoctor.egg-info/SOURCES.txt
DataDoctor.egg-info/dependency_links.txt
DataDoctor.egg-info/requires.txt
DataDoctor.egg-info/top_level.txt
data_doctor/__init__.py
data_doctor/cleaner.py
data_doctor/normalizer.py
data_doctor/utils.py