Metadata-Version: 2.1
Name: DataDoctor
Version: 1.0.13
Summary: A Python package for data cleaning and preprocessing.
Author: Aryan Bajaj
Author-email: aryanbajaj104@email.com
Keywords: data cleaning preprocessing machine learning ML pandas numpy scikit-learn fuzzywuzzy data normalization Artificial Intelligence AI
Classifier: Development Status :: 4 - Beta
Classifier: Intended Audience :: Developers
Classifier: License :: OSI Approved :: MIT License
Classifier: Operating System :: OS Independent
Classifier: Programming Language :: Python :: 3
Classifier: Programming Language :: Python :: 3.6
Classifier: Programming Language :: Python :: 3.7
Classifier: Programming Language :: Python :: 3.8
Classifier: Programming Language :: Python :: 3.9
Classifier: Topic :: Software Development :: Libraries :: Python Modules
License-File: LICENSE.md
